MANIFEST.in
README.txt
setup.py
docs/Makefile
docs/conf.py
docs/index.rst
docs/make.bat
docs/sly.rst
example/calc/calc.py
example/calc_prec/calc.py
sly/__init__.py
sly/lex.py
sly/yacc.py
sly.egg-info/PKG-INFO
sly.egg-info/SOURCES.txt
sly.egg-info/dependency_links.txt
sly.egg-info/requires.txt
sly.egg-info/top_level.txt