Metadata-Version: 1.1
Name: sly
Version: 0.2
Summary: SLY - Sly Lex Yacc
Home-page: https://github.com/dabeaz/sly
Author: David Beazley
Author-email: dave@dabeaz.com
License: BSD
Platform: UNKNOWN
Classifier: Programming Language :: Python :: 3
